{
    "markers": [
        {
            "name": "Renfrewshire Credit Union",
            "body": "Renfrewshire Wide Credit Union was established in 2006 as a merger of 3 smaller credit unions in Erskine, Renfrew and Linwood which has served the local community for over 30 years.",
            "type": "CU",
            "position": { "lat": 55.845025, "lng": -4.426955 },
            "address": "41 High St, Paisley PA1 2AH",
            "link": "http://www.rwcu.co.uk/"
        },
        {
            "name": "Bank of Scotland",
            "body": "Bank of Scotland was founded in 1695, by an Act of the Scottish Parliament - making it Scotland\"s first and oldest bank. It has enjoyed a long and prestigious history, acquiring many constituent companies along the way.",
            "type": "NB",
            "position": { "lat": 55.845838, "lng": -4.423991 },
            "address": "The Cross, Gilmour St, Paisley PA1 1DD",
            "link": "http://www.bankofscotland.co.uk/"
        },
        {
            "name": "TSB Bank",
            "body": "We provide local banking for Britain to help local people, businesses and communities to thrive together.",
            "type": "NB",
            "position": { "lat": 55.845309, "lng": -4.42597 },
            "address": "24 High St, Paisley PA1 2BS",
            "link": "http://www.tsb.co.uk/"
        },
        {
            "name": "Santander",
            "body": "We are Santander Bank, one of the country\"s top retail banks by deposits and a wholly owned subsidiary of one of the most respected banks in the world: Banco Santander. Our parent company, Santander Group, serves more than 100 million customers in the United Kingdom, Latin America, and Europe. Here in the Northeast, we are a team of 9,800 individuals all committed to a single mission: to help you make progress toward your goals. We aim to make your banking hassle-free by providing simple ways for you to spend, save and manage your money.",
            "type": "NB",
            "position": { "lat": 55.84521, "lng": -4.424748 },
            "address": "13-13a High St, Paisley PA1 2AE",
            "link": "http://www.santander.co.uk/uk/index"
        },
        {
            "name": "Financial Advisor",
            "body": "Financial Advisor Bureau is the free service that connects you with an Independent Financial Advisor (IFA) in your area for a free consultation. All IFA\"s on our panel are registered and regulated by the Financial Conduct Authority, the regulatory for the financial services industry in the UK.",
            "type": "FA",
            "position": { "lat": 55.841092, "lng": -4.42411 },
            "address": "67 Causeyside St, Paisley PA1 1YT.",
            "link": "http://financialadvisorbureau.co.uk/"
        },
        {
            "name": "Financial Planning Options",
            "body": "As professional Independent Financial Advisers, Financial Planning Options Limited are authorised to deal with many forms of financial services, and specialise in giving advice to clients on a wide range of subjects to assist with personal and corporate financial planning. We listen to your needs, and offer clear, no-jargon advice on the most appropriate financial products for your personal circumstances.",
            "type": "FA",
            "position": { "lat": 55.841092, "lng": -4.416362 },
            "address": "Suite 49, Abbey Mill Business Centre, PA1 1TJ",
            "link": "http://www.fpoptions.co.uk/"
        },
        {
            "name": "Royal Bank of Scotland",
            "body": "At RBS, our purpose is to serve customers well. We serve around 24 million customers across the globe, and our aim is to consistently meet their needs wherever they find us.",
            "type": "NB",
            "position": { "lat": 55.847842, "lng": -4.42409 },
            "address": "1 Moncrieff St, Paisley PA3 2AW",
            "link": "http://personal.rbs.co.uk/"
        },
        {
            "name": "Advance Financial Strategies",
            "body": "Our service is grounded in the highest professional standards, we acknowledge that all our clients are unique individuals and, as such, deserve bespoke financial solutions tailored to their own financial needs.",
            "type": "FA",
            "position": { "lat": 55.759141, "lng": -4.422215 },
            "address": "19 Glasgow Rd, Paisley PA1 3QX",
            "link": "http://www.advancedfinancialstrategies.co.uk/"
        },
        {
            "name": "Active Works",
            "body": "TODO",
            "type": "FA",
            "position": { "lat": 55.835711, "lng": -4.513791 },
            "address": "25 Church St, Johnston PA5 8DU",
            "link": ""
        },
        {
            "name": "Renfrewshire Council",
            "body": "Always check the local council who can always pass you advice on what to do.",
            "type": "FA",
            "position": { "lat": 55.845122, "lng": -4.419016 },
            "address": "Cotton Street Paisley PA1 1WB",
            "link": "http://www.renfrewshire.gov.uk/"
        },
        {
            "name": "Families First",
            "body": "We bring a range of existing council, health and voluntary services together under the Families First banner to make them easier to find and easier to use.",
            "type": "FA",
            "position": { "lat": 55.848856, "lng": -4.452681 },
            "address": "Paisley PA3 1NS",
            "link": "http://www.renfrewshire.gov.uk/article/2888/Families-First-Renfrewshire"
        },
        {
            "name": "Barnardos Threads",
            "body": "Barnardo’s Threads supports parents, carers and families in the community and in diverse cultural circumstances. Guidance and advice aimed at supporting vulnerable children and their families.",
            "type": "FA",
            "position": { "lat": 55.829373, "lng": -4.420767 },
            "address": "4 Lochfield Road, Paisley PA27BD",
            "link": "http://www.barnardos.org.uk/"
        },
        {
            "name": "Home Start",
            "body": "Home-Start Renfrewshire and Inverclyde is a local independent charity which has been set up to give friendship, advice and practical support to families who live in the Renfrewshire and Inverclyde areas and who have at least one child under the age of 5.",
            "type": "FA",
            "position": { "lat": 55.851011, "lng": -4.424503 },
            "address": "70 Back Sneedon Street Paisley PA32BY",
            "link": "http://www.home-start-renfrewshire.org.uk/"
        },
        {
            "name": "Citizen Advice",
            "body": "Provides local advice tailored to your situation",
            "type": "FA",
            "position": { "lat": 55.842124, "lng": -4.432359 },
            "address": "15 George Street, Paisley PA1 2JX",
            "link": ""
        },
        {
            "name": "Anderson Barr Consultants",
            "body": "For the very best in mortgages, financial advice and pension advice, call Anderson Barr Consultants.",
            "type": "FA",
            "position": { "lat": 55.877644, "lng": -4.389686 },
            "address": "4 Paisley Road, Renfrew, PA48LT",
            "link": "http://www.andersonbarrconsultants.co.uk/"
        },
        {
            "name": "White Cart Credit Union",
            "body": "The White Cart Credit Union is a member of The Association of British Credit Unions Ltd (ABCUL), the leading trade association for credit unions in England, Scotland and Wales.",
            "type": "CU",
            "position": { "lat": 55.834679, "lng": -4.422951 },
            "address": "73 Neilston Road, Paisley, PA2 6NA",
            "link": "http://www.whitecartcu.co.uk/"
        },
        {
            "name": "Gennifer Credit Union",
            "body": "At Gleniffer Credit Union, We Believe in people helping people, ethical business practices, supporting the community, listening to members’ needs, delivering an excellent service, financial services being affordable and accessible, making financial decisions in the interests of the members.",
            "type": "CU",
            "position": { "lat": 55.82298, "lng": -4.431451 },
            "address": "18 Skye Crescent, Paisley, PA2 8EL",
            "link": "http://www.gleniffercreditunion.co.uk/"
        },
        {
            "name": "Nationwide",
            "body": "Whether it’s with the products and services we provide, the charities and causes we support or the communities we serve, everything we do is with our members’ best interests at heart.",
            "type": "NB",
            "position": { "lat": 55.844759, "lng": -4.423508 },
            "address": "10-10A St Mirren St, Paisley PA1 1XW",
            "link": "http://www.nationwide.co.uk/"
        },
        {
            "name": "Clydesdale Bank",
            "body": "With roots back to its establishment in Glasgow in 1838. Clydesdale Bank has a proud history of innovation and support for Scottish industry and communities.",
            "type": "NB",
            "position": { "lat": 55.836357, "lng": -4.510929 },
            "address": "53 High Street Johnstone, PA5 8AJ",
            "link": "http://www.cbonline.co.uk/"
        },
        {
            "name": "TSB Bank",
            "body": "We provide local banking for Britain to help local people, businesses and communities to thrive together.",
            "type": "NB",
            "position": { "lat": 55.837256, "lng": -4.510445 },
            "address": "Rankine St, Johnstone PA5 8AJ",
            "link": "http://www.tsb.co.uk/"
        },
        {
            "name": "Clydesdale Bank",
            "body": "With roots back to its establishment in Glasgow in 1838. Clydesdale Bank has a proud history of innovation and support for Scottish industry and communities.",
            "type": "NB",
            "position": { "lat": 55.844667, "lng": -4.422559 },
            "address": "1 Causeyside St, Paisley PA1 1UW",
            "link": "http://www.cbonline.co.uk/"
        }
    ]
}